<?xml version="1.0"?>
<opencv_storage>
<stage18>
  <maxWeakCount>7</maxWeakCount>
  <stageThreshold>-4.8306906223297119e-01</stageThreshold>
  <weakClassifiers>
    <_>
      <internalNodes>
        0 -1 24601 -72550510 1877616672 -268474864 -1150604640
        -1241524753 -280051887 -294161376 -275814798</internalNodes>
      <leafValues>
        -4.4209635257720947e-01 6.5592461824417114e-01</leafValues></_>
    <_>
      <internalNodes>
        0 -1 95912 -783826814 -1336290750 -478418741 -109369976
        -1983525399 -496050186 -985148257 -1052261689</internalNodes>
      <leafValues>
        -5.0922209024429321e-01 6.2005746364593506e-01</leafValues></_>
    <_>
      <internalNodes>
        0 -1 132659 -662965333 52953226 -1743777679 -113012733
        -1203683073 -1476263552 1224847859 461881483</internalNodes>
      <leafValues>
        -5.2528166770935059e-01 6.3648259639739990e-01</leafValues></_>
    <_>
      <internalNodes>
        0 -1 74205 -748685882 295666028 -1877864320 1968374083
        -754929014 1343258754 134318762 838831747</internalNodes>
      <leafValues>
        -6.2634545564651489e-01 5.0253474712371826e-01</leafValues></_>
    <_>
      <internalNodes>
        0 -1 70718 1140913217 -780665680 1606369279 -1107329025
        -464209450 -16779282 -18469 -534279712</internalNodes>
      <leafValues>
        -5.2222377061843872e-01 6.4257317781448364e-01</leafValues></_>
    <_>
      <internalNodes>
        0 -1 16157 -91576822 -778463134 37889 -1005383678 -1073573576
        -1237171687 -1844866912 -919082413</internalNodes>
      <leafValues>
        -5.6519645452499390e-01 6.0662406682968140e-01</leafValues></_>
    <_>
      <internalNodes>
        0 -1 104936 1343379475 -687270638 -1878945741 1399652417
        140525818 1496453234 429166779 2019627027</internalNodes>
      <leafValues>
        -6.8136876821517944e-01 4.9129557609558105e-01</leafValues></_></weakClassifiers></stage18>
</opencv_storage>
